remedy/__init__.py
remedy/exceptions.py
remedy/remedy.py
remedy_client-0.1.0.dist-info/LICENSE
remedy_client-0.1.0.dist-info/METADATA
remedy_client-0.1.0.dist-info/WHEEL
remedy_client-0.1.0.dist-info/top_level.txt
remedy_client-0.1.0.dist-info/RECORD
